BeritaTerkini/__init__.py
BeritaTerkini/CNN/__init__.py
BeritaTerkini/Kompas/__init__.py
latest_news-0.3.dist-info/METADATA
latest_news-0.3.dist-info/WHEEL
latest_news-0.3.dist-info/top_level.txt
latest_news-0.3.dist-info/RECORD
