Metadata-Version: 2.1
Name: latest-news
Version: 0.3
Summary: This package will get the latest news from the source all website in indonesia
Home-page: https://github.com/017RAFIRAMDHANI/PYTHON.git
Author: Rafi Ramdhani
Author-email: rafiramdhani1122@gmail.com
Classifier: Programming Language :: Python :: 3
Classifier: License :: OSI Approved :: GNU General Public License v3 (GPLv3)
Classifier: Operating System :: OS Independent
Classifier: Development Status :: 5 - Production/Stable
Requires-Python: >=3.6
